HostCount.py
README.md
subnethostcount-0.1.5.dist-info/METADATA
subnethostcount-0.1.5.dist-info/WHEEL
subnethostcount-0.1.5.dist-info/entry_points.txt
subnethostcount-0.1.5.dist-info/RECORD
