Metadata-Version: 2.4
Name: subnethostcount
Version: 0.1.5
Summary: Count usable IPv4 hosts across CIDR subnets and individual IP addresses.
Project-URL: Homepage, https://github.com/DefensiveOrigins/SubnetHostCount
Project-URL: Source, https://github.com/DefensiveOrigins/SubnetHostCount
Project-URL: Issue Tracker, https://github.com/DefensiveOrigins/SubnetHostCount/issues
Author-email: Defensive Origins <info@defensiveorigins.com>
Keywords: cidr,defensive origins,host count,ipv4,networking,subnet
Classifier: Environment :: Console
Classifier: Intended Audience :: System Administrators
Classifier: Programming Language :: Python :: 3
Classifier: Programming Language :: Python :: 3 :: Only
Classifier: Programming Language :: Python :: 3.8
Classifier: Programming Language :: Python :: 3.9
Classifier: Programming Language :: Python :: 3.10
Classifier: Programming Language :: Python :: 3.11
Classifier: Programming Language :: Python :: 3.12
Classifier: Topic :: System :: Networking
Classifier: Topic :: Utilities
Requires-Python: >=3.8
